sibi_dst/__init__.py
sibi_dst/df_helper/__init__.py
sibi_dst/df_helper/_artifact_updater_async.py
sibi_dst/df_helper/_artifact_updater_threaded.py
sibi_dst/df_helper/_df_helper.py
sibi_dst/df_helper/_parquet_artifact.py
sibi_dst/df_helper/_parquet_reader.py
sibi_dst/df_helper/backends/__init__.py
sibi_dst/df_helper/backends/http/__init__.py
sibi_dst/df_helper/backends/http/_http_config.py
sibi_dst/df_helper/backends/parquet/__init__.py
sibi_dst/df_helper/backends/parquet/_parquet_options.py
sibi_dst/df_helper/backends/sqlalchemy/__init__.py
sibi_dst/df_helper/backends/sqlalchemy/_db_connection.py
sibi_dst/df_helper/backends/sqlalchemy/_db_gatekeeper.py
sibi_dst/df_helper/backends/sqlalchemy/_io_dask.py
sibi_dst/df_helper/backends/sqlalchemy/_load_from_db.py
sibi_dst/df_helper/backends/sqlalchemy/_model_registry.py
sibi_dst/df_helper/backends/sqlalchemy/_sql_model_builder.py
sibi_dst/df_helper/core/__init__.py
sibi_dst/df_helper/core/_defaults.py
sibi_dst/df_helper/core/_filter_handler.py
sibi_dst/df_helper/core/_params_config.py
sibi_dst/df_helper/core/_query_config.py
sibi_dst/geopy_helper/__init__.py
sibi_dst/geopy_helper/geo_location_service.py
sibi_dst/geopy_helper/utils.py
sibi_dst/osmnx_helper/__init__.py
sibi_dst/osmnx_helper/base_osm_map.py
sibi_dst/osmnx_helper/route_path_builder.py
sibi_dst/osmnx_helper/utils.py
sibi_dst/osmnx_helper/basemaps/__init__.py
sibi_dst/osmnx_helper/basemaps/calendar_html.py
sibi_dst/osmnx_helper/basemaps/route_map_plotter.py
sibi_dst/osmnx_helper/basemaps/router_plotter.py
sibi_dst/tests/__init__.py
sibi_dst/tests/test_baseclass.py
sibi_dst/tests/test_dask_utils.py
sibi_dst/tests/test_data_wrapper_class.py
sibi_dst/utils/__init__.py
sibi_dst/utils/async_utils.py
sibi_dst/utils/base.py
sibi_dst/utils/business_days.py
sibi_dst/utils/clickhouse_writer.py
sibi_dst/utils/credentials.py
sibi_dst/utils/dask_utils.py
sibi_dst/utils/data_from_http_source.py
sibi_dst/utils/data_utils.py
sibi_dst/utils/data_wrapper.py
sibi_dst-2025.12.2.dist-info/METADATA
sibi_dst-2025.12.2.dist-info/WHEEL
sibi_dst-2025.12.2.dist-info/top_level.txt
sibi_dst-2025.12.2.dist-info/RECORD
