Metadata-Version: 2.4
Name: sibi-dst
Version: 2025.12.2
Summary: A data science toolkit for scalable data processing and analysis.
Requires-Python: >=3.11
Requires-Dist: clickhouse-connect>=0.9.2
Requires-Dist: clickhouse-driver>=0.2.9
Requires-Dist: dask>=2025.9.1
Requires-Dist: distributed>=2025.9.1
Requires-Dist: fastapi>=0.118.0
Requires-Dist: filelock>=3.20.0
Requires-Dist: folium>=0.20.0
Requires-Dist: mysqlclient>=2.2.7
Requires-Dist: opentelemetry-api>=1.37.0
Requires-Dist: opentelemetry-exporter-otlp>=1.37.0
Requires-Dist: opentelemetry-sdk>=1.37.0
Requires-Dist: pandas>=2.3.3
Requires-Dist: psycopg2>=2.9.10
Requires-Dist: pyarrow>=21.0.0
Requires-Dist: pydantic>=2.11.10
Requires-Dist: pydantic-settings>=2.12.0
Requires-Dist: pymysql>=1.1.2
Requires-Dist: redis>=6.4.0
Requires-Dist: rich>=14.2.0
Requires-Dist: s3fs>=2025.9.0
Requires-Dist: sqlalchemy>=2.0.43
Requires-Dist: tqdm>=4.67.1
Requires-Dist: uvicorn>=0.37.0
Requires-Dist: webdav4>=0.10.0
Requires-Dist: wheel>=0.45.1
